0x_contract_artifacts-2.0.0-py3.7-nspkg.pth
zero_ex/contract_artifacts/__init__.py
zero_ex/contract_artifacts/py.typed
zero_ex/contract_artifacts/artifacts/AssetProxyOwner.json
zero_ex/contract_artifacts/artifacts/DummyERC20Token.json
zero_ex/contract_artifacts/artifacts/DummyERC721Token.json
zero_ex/contract_artifacts/artifacts/DutchAuction.json
zero_ex/contract_artifacts/artifacts/ERC20Proxy.json
zero_ex/contract_artifacts/artifacts/ERC20Token.json
zero_ex/contract_artifacts/artifacts/ERC721Proxy.json
zero_ex/contract_artifacts/artifacts/ERC721Token.json
zero_ex/contract_artifacts/artifacts/Exchange.json
zero_ex/contract_artifacts/artifacts/Forwarder.json
zero_ex/contract_artifacts/artifacts/IValidator.json
zero_ex/contract_artifacts/artifacts/IWallet.json
zero_ex/contract_artifacts/artifacts/OrderValidator.json
zero_ex/contract_artifacts/artifacts/WETH9.json
zero_ex/contract_artifacts/artifacts/ZRXToken.json
0x_contract_artifacts-2.0.0.dist-info/METADATA
0x_contract_artifacts-2.0.0.dist-info/WHEEL
0x_contract_artifacts-2.0.0.dist-info/namespace_packages.txt
0x_contract_artifacts-2.0.0.dist-info/top_level.txt
0x_contract_artifacts-2.0.0.dist-info/RECORD
